Metadata-Version: 2.1
Name: YAWeP
Version: 0.0.3
Summary: Yet another weather package api
Home-page: https://gitlab.com/AbhijitL/yawp
Author: Leihaorambam Abhijit Singh
Author-email: labhijitsingh13@gmail.com
Keywords: weather,forecast,openwatherapi
Classifier: Programming Language :: Python :: 3
Classifier: License :: OSI Approved :: MIT License
Classifier: Operating System :: OS Independent
Requires-Python: >=3.6
